{"skeleton":{"hash":"dwncsdD98iI","spine":"4.2.40","x":-590.47,"y":-26.48,"width":1046,"height":1630.86,"images":"","audio":"./audio"},"bones":[{"name":"root"},{"name":"core","parent":"root","x":-58.18,"y":773.8},{"name":"r-leg-1","parent":"core","length":292.43,"rotation":-76.12,"x":78.15,"y":-137.44},{"name":"l-leg-1","parent":"core","length":279.89,"rotation":-93.48,"x":-58.15,"y":-154.96,"scaleY":-1},{"name":"r-leg-2","parent":"r-leg-1","length":292.43,"x":292.43},{"name":"l-leg-2","parent":"l-leg-1","length":279.89,"x":279.89},{"name":"body","parent":"core","length":395.33,"rotation":86.48,"x":-11.99,"y":-47.9},{"name":"head","parent":"body","length":393.97,"rotation":8.65,"x":405.39,"y":16.08},{"name":"l-hair","parent":"head","length":416.42,"rotation":164.8,"x":302.94,"y":218.45,"color":"abe323ff"},{"name":"r-hair","parent":"head","length":432.79,"rotation":-179.88,"x":281.16,"y":-343.99,"color":"abe323ff"},{"name":"l-hair2","parent":"l-hair","length":277.62,"x":416.42,"color":"abe323ff"},{"name":"l-hair3","parent":"l-hair2","length":138.81,"x":277.62,"color":"abe323ff"},{"name":"r-hair2","parent":"r-hair","length":288.52,"x":432.79,"color":"abe323ff"},{"name":"r-hair3","parent":"r-hair2","length":144.26,"x":288.52,"color":"abe323ff"},{"name":"r-hair4","parent":"r-hair3","x":-481.21,"y":-363.44,"color":"abe323ff"},{"name":"f-hair-1","parent":"head","length":160.2,"rotation":154.22,"x":376.61,"y":56.91,"color":"abe323ff"},{"name":"f-hair-2","parent":"head","length":128.13,"rotation":-175.45,"x":362.52,"y":14.87,"color":"abe323ff"},{"name":"f-hair-3","parent":"head","length":142.97,"rotation":-151.56,"x":378.73,"y":-11.33,"color":"abe323ff"},{"name":"f-hair-1b","parent":"f-hair-1","length":106.8,"x":160.2,"color":"abe323ff"},{"name":"f-hair-1c","parent":"f-hair-1b","length":53.4,"x":106.8,"color":"abe323ff"},{"name":"f-hair-2b","parent":"f-hair-2","length":85.42,"x":128.13,"color":"abe323ff"},{"name":"f-hair-2c","parent":"f-hair-2b","length":42.71,"x":85.42,"color":"abe323ff"},{"name":"f-hair-3b","parent":"f-hair-3","length":95.31,"x":142.97,"color":"abe323ff"},{"name":"f-hair-3c","parent":"f-hair-3b","length":47.66,"x":95.31,"color":"abe323ff"},{"name":"l-arm","parent":"body","length":433.78,"rotation":158.11,"x":337.32,"y":69.95,"color":"abe323ff"},{"name":"r-arm","parent":"body","length":435.05,"rotation":-154.44,"x":342.91,"y":-127.62,"color":"abe323ff"},{"name":"sk1","parent":"body","length":133.47,"rotation":143.26,"x":93.86,"y":28.03,"color":"abe323ff"},{"name":"sk2","parent":"body","length":160.64,"rotation":-174.85,"x":97.68,"y":-11.73,"color":"abe323ff"},{"name":"sk3","parent":"body","length":128.54,"rotation":-137.57,"x":103.05,"y":-54.14,"color":"abe323ff"},{"name":"sk1b","parent":"sk1","length":66.73,"x":133.47,"color":"abe323ff"},{"name":"sk2b","parent":"sk2","length":80.32,"rotation":-0.02,"x":160.64,"color":"abe323ff"},{"name":"sk3b","parent":"sk3","length":64.27,"x":128.54,"color":"abe323ff"},{"name":"sk4","parent":"sk2","x":-120.09,"y":581.12,"color":"abe323ff"}],"slots":[{"name":"용지","bone":"root"},{"name":"왼다","bone":"root","attachment":"왼다"},{"name":"오다","bone":"root","attachment":"오다"},{"name":"왼팔","bone":"root","attachment":"왼팔"},{"name":"치마","bone":"root","attachment":"치마"},{"name":"몸통","bone":"root","attachment":"몸통"},{"name":"오른팔","bone":"root","attachment":"오른팔"},{"name":"왼머","bone":"root","attachment":"왼머"},{"name":"머리","bone":"root","attachment":"머리"},{"name":"앞머리","bone":"root","attachment":"앞머리"},{"name":"오머","bone":"root","attachment":"오머"}],"physics":[{"name":"f-hair-1","order":12,"bone":"f-hair-1","rotate":1,"inertia":0.5,"damping":0.85},{"name":"f-hair-1b","order":13,"bone":"f-hair-1b","rotate":1,"inertia":0.5,"damping":0.85},{"name":"f-hair-1c","order":14,"bone":"f-hair-1c","rotate":1,"inertia":0.5,"damping":0.85},{"name":"f-hair-2","order":9,"bone":"f-hair-2","rotate":1,"inertia":0.5,"damping":0.85},{"name":"f-hair-2b","order":10,"bone":"f-hair-2b","rotate":1,"inertia":0.5,"damping":0.85},{"name":"f-hair-2c","order":11,"bone":"f-hair-2c","rotate":1,"inertia":0.5,"damping":0.85},{"name":"f-hair-3","order":6,"bone":"f-hair-3","rotate":1,"inertia":0.5,"damping":0.85},{"name":"f-hair-3b","order":7,"bone":"f-hair-3b","rotate":1,"inertia":0.5,"damping":0.85},{"name":"f-hair-3c","order":8,"bone":"f-hair-3c","rotate":1,"inertia":0.5,"damping":0.85},{"name":"l-arm","order":22,"bone":"l-arm","rotate":1,"limit":5050,"inertia":0.3253,"strength":63.9,"damping":0.85},{"name":"l-hair","order":3,"bone":"l-hair","rotate":1,"inertia":0.5,"damping":0.85},{"name":"l-hair2","order":4,"bone":"l-hair2","rotate":1,"inertia":0.5,"damping":0.85},{"name":"l-hair3","order":5,"bone":"l-hair3","rotate":1,"inertia":0.5,"damping":0.85},{"name":"r-arm","order":21,"bone":"r-arm","rotate":1,"limit":5050,"inertia":0.3253,"strength":63.9,"damping":0.85},{"name":"r-hair","bone":"r-hair","rotate":1,"inertia":0.5,"damping":0.85},{"name":"r-hair2","order":1,"bone":"r-hair2","rotate":1,"inertia":0.5,"damping":0.85},{"name":"r-hair3","order":2,"bone":"r-hair3","rotate":1,"inertia":0.5,"damping":0.85},{"name":"sk1","order":19,"bone":"sk1","rotate":1,"inertia":0.5,"damping":0.85},{"name":"sk1b","order":20,"bone":"sk1b","rotate":1,"inertia":0.5,"damping":0.85},{"name":"sk2","order":17,"bone":"sk2","rotate":1,"inertia":0.5,"damping":0.85},{"name":"sk2b","order":18,"bone":"sk2b","rotate":1,"inertia":0.5,"damping":0.85},{"name":"sk3","order":15,"bone":"sk3","rotate":1,"inertia":0.5,"damping":0.85},{"name":"sk3b","order":16,"bone":"sk3b","rotate":1,"inertia":0.5,"damping":0.85}],"skins":[{"name":"default","attachments":{"머리":{"머리":{"type":"mesh","uvs":[1,1,0,1,0,0,1,0],"triangles":[1,2,3,1,3,0],"vertices":[1,7,-54.95,-297.15,1,1,7,-6.79,238.69,1,1,7,492.2,193.84,1,1,7,444.03,-342,1],"hull":4,"edges":[0,2,2,4,4,6,0,6],"width":538,"height":501}},"몸통":{"몸통":{"type":"mesh","uvs":[1,1,0,1,0,0.5,0,0,1,0,1,0.5],"triangles":[0,1,5,1,2,5,5,2,4,2,3,4],"vertices":[1,6,-33.95,-157.07,1,1,6,-50.45,111.42,1,1,6,169.14,124.92,1,1,6,388.72,138.41,1,1,6,405.22,-130.08,1,1,6,185.64,-143.58,1],"hull":6,"edges":[0,2,2,4,4,6,6,8,8,10,10,0],"width":269,"height":440}},"앞머리":{"앞머리":{"type":"mesh","uvs":[0.46197,0,0.71474,0.0119,0.93791,0.1964,1,0.56108,1,0.68167,0.96038,0.82925,0.60285,0.46826,0.60921,0.58229,0.67265,0.84403,0.29993,0.47674,0.1785,0.68214,0.19332,1,0.18636,1,0.10604,0.95993,0.00972,0.79896,0,0.48882,0,0.35883,0.17823,0.08387,0.36784,0],"triangles":[3,4,6,6,4,5,6,2,3,6,1,2,6,0,1,9,7,8,9,6,7,12,13,11,13,10,11,13,14,10,14,15,10,10,15,9,15,16,9,6,9,0,9,18,0,16,17,9,9,17,18],"vertices":[3,15,-65.39,34.11,0.38683,16,-56.6,21.68,0.21666,17,-41.2,11.99,0.39651,2,17,18.04,92.5,0.99998,22,-124.92,92.5,2.0E-5,2,17,129.2,124.52,0.82307,22,-13.76,124.52,0.17693,3,17,266.13,63.07,3.6E-4,22,123.16,63.07,0.38112,23,27.84,63.07,0.61853,1,23,68.63,35.99,1,1,23,109.9,-10.18,1,4,16,140.17,44.54,0.17272,20,12.04,44.54,0.57872,17,147.97,-46.79,0.08213,22,5,-46.79,0.16643,3,20,58.1,39.23,0.99862,21,-27.32,39.23,8.7E-4,22,44.96,-70.3,5.1E-4,1,21,81.65,46.04,1,4,15,138.3,42.45,0.76855,18,-21.9,42.45,0.05959,16,123.43,-73.98,0.06728,20,-4.7,-73.98,0.10459,1,18,73.04,26.96,1,1,19,84.94,77.93,1,1,19,85.91,75.36,1,1,19,81.87,39.94,1,2,18,140.93,-18.71,0.05755,19,34.13,-18.71,0.94245,3,15,184.65,-66.69,0.29686,18,24.45,-66.69,0.70127,19,-82.35,-66.69,0.00187,2,15,135.27,-85.29,0.6806,18,-24.94,-85.29,0.3194,1,15,5.98,-58.77,1,3,15,-52.29,-0.68,0.85593,16,-62.85,-14.97,0.07744,17,-61.76,-18.99,0.06663],"hull":19,"edges":[0,36,0,2,2,4,4,6,6,8,8,10,10,12,12,14,14,16,16,18,18,20,20,22,22,24,24,26,26,28,28,30,30,32,32,34,34,36],"width":395,"height":406}},"오다":{"오다":{"type":"mesh","uvs":[0.35757,0.03059,0.50544,0.18314,0.77729,0.46358,1,0.82513,0.95435,0.978,0.60335,1,0.29146,0.97107,0.151,0.76001,0.10898,0.45529,0.09338,0.39772,0.07678,0.33649,1.0E-5,0.05332,0.14428,0],"triangles":[7,8,2,7,2,3,5,6,7,7,3,5,4,5,3,11,1,10,0,11,12,1,11,0,2,9,10,2,8,9,1,2,10],"vertices":[1,2,9.14,57.72,1,2,2,115.43,73.63,0.97478,4,-177.01,73.63,0.02522,2,2,310.82,102.88,0.17423,4,18.39,102.88,0.82577,1,4,262.75,107.57,1,1,4,357.82,73.44,1,1,4,351.17,-20.45,1,1,4,314.25,-96.8,1,2,2,463.42,-102.24,0.03714,4,170.99,-102.24,0.96286,2,2,266.06,-68.56,0.86522,4,-26.37,-68.56,0.13478,2,2,228.33,-64.18,0.7455,4,-64.11,-64.18,0.2545,2,2,188.19,-59.52,0.8272,4,-104.24,-59.52,0.1728,1,2,2.56,-37.97,1,1,2,-23.02,7.09,1],"hull":13,"edges":[4,6,8,10,12,14,14,16,10,12,6,8,22,24,24,0,16,18,18,20,20,22,0,2,2,4],"width":265,"height":656}},"오른팔":{"오른팔":{"type":"mesh","uvs":[1,1,0,1,0,0,1,0],"triangles":[1,2,3,1,3,0],"vertices":[1,25,532.29,3.8,1,1,25,442.22,-218.65,1,1,25,-44.41,-21.64,1,1,25,45.66,200.82,1],"hull":4,"edges":[0,2,2,4,4,6,0,6],"width":240,"height":525}},"오머":{"오머":{"type":"mesh","uvs":[0.53087,0,0.61158,0.05032,0.90884,0.45194,1,0.67828,0.58221,0.78052,0.84655,0.86987,0.56232,1,0.3283,0.97072,0.24347,0.9102,0.40568,0.85475,0.17053,0.72459,0.2897,0.49809,0.34173,0.33335,0.26715,0.16157,0.21615,0.11884,5.0E-5,0.04834],"triangles":[7,9,6,6,9,5,7,8,9,9,4,5,9,10,4,4,10,3,10,11,3,11,2,3,11,12,2,12,1,2,12,13,1,13,14,1,14,0,1,14,15,0],"vertices":[1,9,-62.51,74.13,1,1,9,-7.72,91.78,1,2,9,420.63,135.92,0.58539,12,-12.16,135.92,0.41461,2,12,227.29,139.51,0.99859,13,-61.24,139.51,0.00141,2,12,323.66,13.16,0.02887,13,35.14,13.16,0.97113,1,13,135.53,78.24,1,1,13,264.55,-13.56,1,1,13,227.87,-75.98,1,1,13,162.3,-93.8,1,1,13,108.37,-43.22,1,2,12,254.51,-96.23,0.84054,13,-34.02,-96.23,0.15946,2,9,453.07,-41.16,0.0257,12,20.29,-41.16,0.9743,1,9,281.83,-10.76,1,1,9,99.97,-14.99,1,1,9,53.9,-25.08,1,1,9,-25.5,-78.54,1],"hull":16,"edges":[0,2,2,4,4,6,10,12,14,16,16,18,20,22,22,24,24,26,26,28,18,20,8,10,12,14,6,8,30,0,28,30],"width":280,"height":1052}},"왼다":{"왼다":{"type":"mesh","uvs":[0.92906,0.06921,0.90932,0.27409,0.90431,0.32613,0.89933,0.37786,1,0.90584,1,0.99595,0.32191,1,0.05826,0.92154,0,0.68235,0,0.62221,0.17632,0.40907,0.337,0.11279,0.47836,0.00398],"triangles":[5,6,4,6,7,4,7,8,4,4,8,3,3,8,9,3,9,10,3,10,2,1,2,10,1,10,11,1,11,0,11,12,0],"vertices":[1,3,24.61,48.29,1,2,3,159.66,50.99,0.73122,5,-120.23,50.99,0.26878,2,3,193.97,51.68,0.60921,5,-85.92,51.68,0.39079,2,3,228.07,52.36,0.55338,5,-51.83,52.36,0.44662,1,5,294.61,90.97,1,1,5,353.91,93.97,1,1,5,363.74,-47.43,1,1,5,314.89,-105.08,1,2,3,437.97,-125.21,0.21167,5,158.08,-125.21,0.78833,2,3,398.39,-127.21,0.25143,5,118.5,-127.21,0.74857,2,3,256.25,-97.51,0.41378,5,-23.64,-97.51,0.58622,1,3,59.55,-73.84,1,1,3,-13.56,-47.96,1],"hull":13,"edges":[8,10,12,14,14,16,16,18,18,20,22,24,20,22,10,12,24,0,4,6,6,8,0,2,2,4],"width":209,"height":659}},"왼머":{"왼머":{"type":"mesh","uvs":[0.99948,0.00675,0.99533,0.18649,0.70384,0.42332,0.62574,0.58981,0.77003,0.74794,0.5838,1,0.5605,1,0.16755,0.9251,0.29209,0.82345,0.469,0.75634,0.11925,0.68638,0,0.6369,0.25251,0.47322,0.40978,0.35999,0.76371,0],"triangles":[4,5,8,7,8,6,5,6,8,4,8,9,4,9,3,9,10,3,10,11,3,11,12,3,3,12,2,12,13,2,2,13,1,13,14,1,1,14,0],"vertices":[1,8,-82.2,40.65,1,1,8,98.21,71.23,1,1,8,352.86,16.06,1,1,10,107.94,19.59,1,2,10,257.9,95.88,0.58649,11,-19.72,95.88,0.41351,1,11,243.96,78.54,1,1,11,245.34,70.76,1,1,11,193.53,-73.72,1,2,10,361.89,-50.22,1.0E-5,11,84.27,-50.22,0.99999,2,10,284.14,-3.11,0.22113,11,6.52,-3.11,0.77887,1,10,234.73,-132.29,1,1,10,192.19,-180.9,1,2,8,429.6,-125.72,0.33787,10,13.18,-125.72,0.66213,2,8,306.79,-93.36,0.98186,10,-109.63,-93.36,0.01814,1,8,-75,-39.24,1],"hull":15,"edges":[0,2,2,4,4,6,6,8,8,10,10,12,12,14,14,16,16,18,18,20,22,24,24,26,26,28,28,0,20,22],"width":339,"height":1018}},"왼팔":{"왼팔":{"type":"mesh","uvs":[1,1,0,1,0,0,1,0],"triangles":[1,2,3,1,3,0],"vertices":[1,24,397.55,213,1,1,24,515.97,-36.31,1,1,24,92.34,-237.53,1,1,24,-26.08,11.77,1],"hull":4,"edges":[0,2,2,4,4,6,0,6],"width":276,"height":469}},"용지":{"용지":{"width":1460,"height":1880}},"치마":{"치마":{"type":"mesh","uvs":[1,0.54352,0.82414,0.88364,0.51944,0.99999,0.11039,0.90619,0,0.59495,0.38752,0,0.62547,0.00487],"triangles":[1,6,0,2,5,6,2,6,1,2,3,4,2,4,5],"vertices":[1,31,68.83,33.86,1,3,27,232.63,116.59,0.00475,30,71.99,116.59,0.45033,31,102.51,-83.06,0.54493,4,29,39.18,201.41,0.00723,30,102.61,-5.31,0.9924,28,181.59,-198.6,1.0E-5,31,53.05,-198.6,3.6E-4,2,29,123.16,59.73,0.74057,30,70.5,-166.85,0.25943,2,29,81.89,-32.65,1,28,-40.28,-284.5,0,3,26,-17.1,-27.9,0.95261,27,-31.12,-49.29,0.04739,28,-79.28,-55.3,0,3,26,-77.06,45.11,8.0E-5,27,-27,45.1,0.08955,28,-18.83,17.31,0.91037],"hull":7,"edges":[0,12,4,6,8,10,10,12,6,8,0,2,2,4],"width":397,"height":293}}}}],"animations":{"Standing":{"bones":{"body":{"translate":[{},{"time":0.4667,"y":-36.22},{"time":1}]},"core":{"translate":[{"time":0.3333,"x":0.15,"y":-4.63}]},"r-hair":{"rotate":[{},{"time":0.5,"value":14.48},{"time":1}]},"l-hair":{"rotate":[{},{"time":0.5,"value":-10.06},{"time":1}],"translate":[{},{"time":0.5,"x":26.96},{"time":1}]}}},"work":{"bones":{"core":{"translate":[{"y":-102.47},{"time":0.1667,"y":-42.08},{"time":0.3333,"y":-9.34},{"time":0.5,"y":-71.91},{"time":0.6667,"y":-102.47,"curve":"stepped"},{"time":0.8333,"y":-102.47},{"time":1,"y":-44.37,"curve":"stepped"},{"time":1.1667,"y":-44.37},{"time":1.3333,"y":-102.47}]},"l-leg-1":{"rotate":[{"value":-22.66},{"time":0.1667,"value":-19.59},{"time":0.3333,"value":15.01},{"time":0.5,"value":10.3},{"time":0.6667,"value":16.42},{"time":1,"value":-7.79},{"time":1.1667,"value":-35.56},{"time":1.3333,"value":-25.2}]},"l-leg-2":{"rotate":[{"value":-5.95},{"time":0.1667,"value":-31.67},{"time":0.3333,"value":0.27},{"time":0.5,"value":-17.8},{"time":0.6667,"value":-32.29},{"time":0.8333,"value":-61.84},{"time":1,"value":-67.7},{"time":1.3333,"value":-7.35}]},"r-leg-1":{"rotate":[{"value":2.81},{"time":0.1667,"value":-15.75},{"time":0.3333,"value":-39.99},{"time":0.5,"value":-40.49},{"time":1,"value":-8.51},{"time":1.1667,"value":6.41}]},"r-leg-2":{"rotate":[{"value":39.29},{"time":0.1667,"value":56.96},{"time":0.3333,"value":78.34},{"time":0.5,"value":22.45},{"time":0.6667,"value":8.11},{"time":0.8333,"value":24.83},{"time":1,"value":-3.79},{"time":1.1667,"value":-0.72},{"time":1.3333,"value":39.29}]},"l-arm":{"rotate":[{"value":27.41},{"time":0.3333,"value":-11.23},{"time":1.1667,"value":37.07},{"time":1.3333,"value":27.41}]},"r-arm":{"rotate":[{"value":-28.26},{"time":0.5,"value":11.83},{"time":1.1667,"value":-62.52},{"time":1.3333,"value":-28.26}]},"l-hair":{"rotate":[{"value":-18.95},{"time":0.3333},{"time":0.6667,"value":-18.95},{"time":1},{"time":1.3333,"value":-18.95}]},"r-hair":{"rotate":[{"value":15.67},{"time":0.3333},{"time":0.6667,"value":15.67},{"time":1},{"time":1.3333,"value":15.67}]}},"attachments":{"default":{"몸통":{"몸통":{"deform":[{"vertices":[-1.40283,2.0273,1.16486,2.17276,1.28387,0.07269,1.40289,-2.02735,-1.16492,-2.17281,-1.28387,-0.07273]}]}}}}}}}